MyPiano/__init__.py
MyPiano/__main__.py
MyPiano/config.py
MyPiano/midi2notes.py
MyPiano/play_midi.py
MyPiano/play_note.py
MyPiano/data/FreeSound/a#0.wav
MyPiano/data/FreeSound/a#1.wav
MyPiano/data/FreeSound/a#2.wav
MyPiano/data/FreeSound/a#3.wav
MyPiano/data/FreeSound/a#4.wav
MyPiano/data/FreeSound/a#5.wav
MyPiano/data/FreeSound/a#6.wav
MyPiano/data/FreeSound/a#7.wav
MyPiano/data/FreeSound/a0.wav
MyPiano/data/FreeSound/a1.wav
MyPiano/data/FreeSound/a2.wav
MyPiano/data/FreeSound/a3.wav
MyPiano/data/FreeSound/a4.wav
MyPiano/data/FreeSound/a5.wav
MyPiano/data/FreeSound/a6.wav
MyPiano/data/FreeSound/a7.wav
MyPiano/data/FreeSound/b0.wav
MyPiano/data/FreeSound/b1.wav
MyPiano/data/FreeSound/b2.wav
MyPiano/data/FreeSound/b3.wav
MyPiano/data/FreeSound/b4.wav
MyPiano/data/FreeSound/b5.wav
MyPiano/data/FreeSound/b6.wav
MyPiano/data/FreeSound/b7.wav
MyPiano/data/FreeSound/c#1.wav
MyPiano/data/FreeSound/c#2.wav
MyPiano/data/FreeSound/c#3.wav
MyPiano/data/FreeSound/c#4.wav
MyPiano/data/FreeSound/c#5.wav
MyPiano/data/FreeSound/c#6.wav
MyPiano/data/FreeSound/c#7.wav
MyPiano/data/FreeSound/c1.wav
MyPiano/data/FreeSound/c2.wav
MyPiano/data/FreeSound/c3.wav
MyPiano/data/FreeSound/c4.wav
MyPiano/data/FreeSound/c5.wav
MyPiano/data/FreeSound/c6.wav
MyPiano/data/FreeSound/c7.wav
MyPiano/data/FreeSound/c8.wav
MyPiano/data/FreeSound/d#1.wav
MyPiano/data/FreeSound/d#2.wav
MyPiano/data/FreeSound/d#3.wav
MyPiano/data/FreeSound/d#4.wav
MyPiano/data/FreeSound/d#5.wav
MyPiano/data/FreeSound/d#6.wav
MyPiano/data/FreeSound/d#7.wav
MyPiano/data/FreeSound/d1.wav
MyPiano/data/FreeSound/d2.wav
MyPiano/data/FreeSound/d3.wav
MyPiano/data/FreeSound/d4.wav
MyPiano/data/FreeSound/d5.wav
MyPiano/data/FreeSound/d6.wav
MyPiano/data/FreeSound/d7.wav
MyPiano/data/FreeSound/e1.wav
MyPiano/data/FreeSound/e2.wav
MyPiano/data/FreeSound/e3.wav
MyPiano/data/FreeSound/e4.wav
MyPiano/data/FreeSound/e5.wav
MyPiano/data/FreeSound/e6.wav
MyPiano/data/FreeSound/e7.wav
MyPiano/data/FreeSound/f#1.wav
MyPiano-0.0.1.dist-info/LICENSE
MyPiano-0.0.1.dist-info/METADATA
MyPiano-0.0.1.dist-info/WHEEL
MyPiano-0.0.1.dist-info/entry_points.txt
MyPiano-0.0.1.dist-info/top_level.txt
MyPiano-0.0.1.dist-info/RECORD
