Metadata-Version: 2.1
Name: MyPiano
Version: 0.0.1
Summary: Play simple notes or MIDI files
Home-page: http://github.com/dilawar/MyPiano
Author: Dilawar Singh
Author-email: dilawars@ncbs.res.in
License: GPLv3
Platform: UNKNOWN
Requires-Dist: mido
Requires-Dist: soundfile
Requires-Dist: sounddevice
